morcilla/__init__.py
morcilla/core.py
morcilla/importer.py
morcilla/interfaces.py
morcilla/py.typed
morcilla/backends/__init__.py
morcilla/backends/asyncpg.py
morcilla/backends/sqlite.py
morcilla-0.5.37.dist-info/LICENSE.md
morcilla-0.5.37.dist-info/METADATA
morcilla-0.5.37.dist-info/WHEEL
morcilla-0.5.37.dist-info/top_level.txt
morcilla-0.5.37.dist-info/RECORD
