Metadata-Version: 2.1
Name: morcilla
Version: 0.5.37
Summary: Performant async database support for Python.
Home-page: https://github.com/athenianco/morcilla
Author: Tom Christie
Author-email: tom@tomchristie.com
License: BSD
Classifier: Development Status :: 3 - Alpha
Classifier: Environment :: Web Environment
Classifier: Intended Audience :: Developers
Classifier: License :: OSI Approved :: BSD License
Classifier: Operating System :: OS Independent
Classifier: Topic :: Internet :: WWW/HTTP
Classifier: Programming Language :: Python :: 3
Classifier: Programming Language :: Python :: 3.6
Classifier: Programming Language :: Python :: 3.7
Classifier: Programming Language :: Python :: 3.8
Classifier: Programming Language :: Python :: 3.9
Classifier: Programming Language :: Python :: 3.10
Classifier: Programming Language :: Python :: 3.11
Classifier: Programming Language :: Python :: 3 :: Only
Requires-Python: >=3.8
License-File: LICENSE.md
Requires-Dist: sqlalchemy (<1.5,>=1.4.42)
Provides-Extra: postgresql
Requires-Dist: asyncpg-rkt ; extra == 'postgresql'
Provides-Extra: sqlite
Requires-Dist: aiosqlite ; extra == 'sqlite'
